flask_profiler/__init__.py
flask_profiler/static/css/daisyui.css
flask_profiler/static/css/dataTable.css
flask_profiler/static/css/tailwindcss.css
flask_profiler/static/js/alpine.js
flask_profiler/static/js/dataTable.js
flask_profiler/static/js/echarts.min.js
flask_profiler/static/js/htmx.min.js
flask_profiler/static/js/jquery.js
flask_profiler/static/js/tailwindcss.js
flask_profiler/static/python-flask.png
flask_profiler/storage/__init__.py
flask_profiler/storage/base.py
flask_profiler/storage/mongo.py
flask_profiler/storage/sql_alchemy.py
flask_profiler/storage/sqlite.py
flask_profiler/tailwind.config.js
flask_profiler/templates/dashboard.html
flask_profiler/templates/filtering.html
flask_profiler/templates/head.html
flask_profiler/templates/header.html
flask_profiler/templates/settings.html
profiler_flask-0.1.0.dist-info/METADATA
profiler_flask-0.1.0.dist-info/WHEEL
profiler_flask-0.1.0.dist-info/RECORD
