Metadata-Version: 2.1
Name: Profiler-Flask
Version: 0.1.0
Summary: Monitor and analyze flask endpoint and request performance.
Author-Email: Dumbliidore <2361018131@qq.com>
License: MIT
Classifier: Programming Language :: Python :: 3.11
Classifier: License :: OSI Approved :: MIT License
Project-URL: Homepage, https://pypi.org/project/profiler-flask
Project-URL: Source code, https://github.com/Dumbliidore/profiler-flask
Requires-Python: >=3.11
Requires-Dist: flask>=3.0.2
Requires-Dist: flask-httpauth>=4.8.0
